sekve/__init__.py
sekve/docstring.py
sekve/model.py
sekve/utils.py
sekve/extractor/__init__.py
sekve/extractor/gds_extractor.py
sekve/extractor/sekv_extractor.py
sekve/extractor/ss_extractor.py
sekve/logger/__init__.py
sekve/plotting/__init__.py
sekve/plotting/plot.py
sekve/tests/__init__.py
sekve-1.1.5.dist-info/LICENSE
sekve-1.1.5.dist-info/METADATA
sekve-1.1.5.dist-info/WHEEL
sekve-1.1.5.dist-info/top_level.txt
sekve-1.1.5.dist-info/RECORD
