Metadata-Version: 2.1
Name: sekve
Version: 1.1.5
Summary: SEKV-E is a Python-based parameters extractor for the simplified EKV model.
Home-page: https://gitlab.com/moscm/sekv-e
Author: Hung-Chi Han, Vicente Carbon
Author-email: hung.han@epfl.ch
License: MIT
Project-URL: Git, https://gitlab.com/moscm/sekv-e
Keywords: ekv,sekv,extractor,modeling,MOSFET
Classifier: Development Status :: 3 - Alpha
Classifier: Intended Audience :: Science/Research
Classifier: Topic :: Scientific/Engineering
Classifier: License :: OSI Approved :: MIT License
Classifier: Programming Language :: Python :: 3
Classifier: Programming Language :: Python :: 3.8
Classifier: Programming Language :: Python :: 3.9
Classifier: Programming Language :: Python :: 3.10
Classifier: Programming Language :: Python :: 3 :: Only
Requires-Python: >=3.7, <4
License-File: LICENSE
Requires-Dist: matplotlib
Requires-Dist: numpy
Requires-Dist: pandas
Requires-Dist: scipy
